diasapi/__init__.py
diasapi/api.py
diasapi-0.4a3.dist-info/LICENSE
diasapi-0.4a3.dist-info/METADATA
diasapi-0.4a3.dist-info/WHEEL
diasapi-0.4a3.dist-info/top_level.txt
diasapi-0.4a3.dist-info/RECORD
