Metadata-Version: 2.1
Name: diasapi
Version: 0.4a3
Summary: Python Client Library for accessing CMCC data
Home-page: https://github.com/CMCC-Foundation/CMCC-DIAS-Client/diasapi/diasapi
Author: Marco Mancini
Author-email: marco.mancini@cmcc.it
License: Apache License, Version 2.0
Platform: UNKNOWN
Classifier: Development Status :: 3 - Alpha
Classifier: Environment :: Web Environment
Classifier: Intended Audience :: Science/Research
Classifier: License :: OSI Approved :: Apache Software License
Classifier: Natural Language :: English
Classifier: Operating System :: OS Independent
Classifier: Programming Language :: Python :: 3
Classifier: Topic :: Scientific/Engineering :: Atmospheric Science
Classifier: Topic :: Scientific/Engineering :: Hydrology
Requires-Python: >=3.7
Requires-Dist: netCDF4 (>=1.5.3)
Requires-Dist: scipy (>=1.5.2)
Requires-Dist: requests (>=2.23.0)
Requires-Dist: xarray (==0.16.0)
